ctft/__init__.py
ctft/ctftime_scrape.py
ctft/formatter.py
ctft/get_event_url.py
ctft/get_writeup_url.py
ctft/github_scrape.py
ctft/souper.py
ctft-0.1.11.data/scripts/ctft
ctft-0.1.11.dist-info/LICENSE
ctft-0.1.11.dist-info/METADATA
ctft-0.1.11.dist-info/WHEEL
ctft-0.1.11.dist-info/top_level.txt
ctft-0.1.11.dist-info/RECORD
