Metadata-Version: 2.1
Name: ctft
Version: 0.1.11
Summary: CLI tool to get and view stylised CTFTime.org writeups in your terminal.
Home-page: https://github.com/bajatin/ctft
Author: JATIN BAGHEL
Author-email: jatinbaghel@protonmail.com
License: MIT
Platform: UNKNOWN
Classifier: License :: OSI Approved :: MIT License
Classifier: Programming Language :: Python
Classifier: Programming Language :: Python :: 3
Classifier: Programming Language :: Python :: 3.6
Classifier: Programming Language :: Python :: Implementation :: CPython
Classifier: Programming Language :: Python :: Implementation :: PyPy
Requires-Python: >=3.6.0
Requires-Dist: aiohttp
Requires-Dist: bs4
Requires-Dist: html2text
Requires-Dist: inquirer
Requires-Dist: requests
Requires-Dist: vmd
